idktrans/__init__.py
idktrans/_version.py
idktrans/io.py
cdl_idk_trans-0.3.4.dist-info/METADATA
cdl_idk_trans-0.3.4.dist-info/WHEEL
cdl_idk_trans-0.3.4.dist-info/top_level.txt
cdl_idk_trans-0.3.4.dist-info/RECORD
