Metadata-Version: 2.1
Name: cdl-idk-trans
Version: 0.3.4
Summary: Tools for building insight generators
Home-page: UNKNOWN
Author: eden.trainor@compassdigital.io
License: UNKNOWN
Platform: UNKNOWN
Requires-Python: >=3.6
